anndi/__init__.py
anndi-0.2.dist-info/DESCRIPTION.rst
anndi-0.2.dist-info/METADATA
anndi-0.2.dist-info/RECORD
anndi-0.2.dist-info/WHEEL
anndi-0.2.dist-info/metadata.json
anndi-0.2.dist-info/top_level.txt
