Metadata-Version: 2.0
Name: anndi
Version: 0.2
Summary: Experimental dependency injection that uses annotations.
Home-page: https://github.com/nvbn/anndi
Author: Vladimir Iakovlev
Author-email: nvbn.rm@gmail.com
License: MIT
Platform: UNKNOWN
